package_potato/Config.py
package_potato/Screen.py
package_potato/TimerEngine.py
package_potato/UserInterface.py
package_potato/__init__.py
potatotimer/Config.py
potatotimer/Screen.py
potatotimer/TimerEngine.py
potatotimer/UserInterface.py
potatotimer/__init__.py
potatotimer-0.2.4.data/scripts/potatotimer
potatotimer-0.2.4.dist-info/LICENSE
potatotimer-0.2.4.dist-info/METADATA
potatotimer-0.2.4.dist-info/WHEEL
potatotimer-0.2.4.dist-info/top_level.txt
potatotimer-0.2.4.dist-info/RECORD
