Metadata-Version: 2.1
Name: potatotimer
Version: 0.2.4
Summary: A simple pomodoro style timer
Home-page: https://github.com/mtijas/potato-timer
Author: Markus Ijäs
License: MIT
Platform: UNKNOWN
Requires-Python: >=3.7.0
Requires-Dist: appdirs (>=1.4.4)
Requires-Dist: PyYAML (>=5.4.1)
